pyBaseSwap/IERC20.py
pyBaseSwap/ISwapperContract.py
pyBaseSwap/SwapperModul.py
pyBaseSwap/W3Utils.py
pyBaseSwap/__init__.py
pyBaseSwap/core_abis.py
pyBaseSwap/core_chains.py
pyBaseSwap/core_settings.py
pyBaseSwap-0.14.dist-info/LICENSE
pyBaseSwap-0.14.dist-info/METADATA
pyBaseSwap-0.14.dist-info/WHEEL
pyBaseSwap-0.14.dist-info/top_level.txt
pyBaseSwap-0.14.dist-info/RECORD
