Metadata-Version: 2.1
Name: pyBaseSwap
Version: 0.14
Summary: A Python library for aggregating token prices and swaps across multiple DEXs
Home-page: https://github.com/BasedTools/pyBaseSwap
Author: BasedTools
Author-email: BasedToolsAdmin@protonmail.com"
License: MIT
Classifier: Programming Language :: Python :: 3
Classifier: License :: OSI Approved :: MIT License
Classifier: Programming Language :: Python :: 3.8
Classifier: Programming Language :: Python :: 3.9
Classifier: Programming Language :: Python :: 3.10
Classifier: Intended Audience :: Developers
Classifier: Topic :: Software Development :: Libraries
Requires-Python: >=3.6
License-File: LICENSE
Requires-Dist: requests
Requires-Dist: web3
Requires-Dist: eth-abi
